[
  {
    "id": "HSK1_001",
    "hsk": 1,
    "chinese": "今天虽然很忙，但是我还是想给妈妈打电话。",
    "answer": "Hôm nay tuy rất bận nhưng tôi vẫn muốn gọi điện cho mẹ.",
    "keywords": [
      "今天",
      "忙",
      "妈妈",
      "打电话"
    ],
    "difficulty": 2,
    "tags": [
      "family",
      "daily-life"
    ]
  },
  {
    "id": "HSK1_002",
    "hsk": 1,
    "chinese": "下雨的时候，我喜欢在家看书和听音乐。",
    "answer": "Khi trời mưa, tôi thích ở nhà đọc sách và nghe nhạc.",
    "keywords": [
      "下雨",
      "喜欢",
      "看书",
      "听音乐"
    ],
    "difficulty": 2,
    "tags": [
      "daily-life",
      "study"
    ]
  },
  {
    "id": "HSK1_003",
    "hsk": 1,
    "chinese": "朋友来了以后，我们一起吃饭，也一起聊天。",
    "answer": "Sau khi bạn đến, chúng tôi cùng ăn cơm và trò chuyện.",
    "keywords": [
      "朋友",
      "一起",
      "吃饭",
      "聊天"
    ],
    "difficulty": 2,
    "tags": [
      "friends",
      "daily-life"
    ]
  },
  {
    "id": "HSK1_004",
    "hsk": 1,
    "chinese": "我每天早上七点起床，然后去学校学习汉语。",
    "answer": "Mỗi sáng tôi thức dậy lúc bảy giờ, sau đó đến trường học tiếng Trung.",
    "keywords": [
      "每天",
      "早上",
      "起床",
      "学校"
    ],
    "difficulty": 2,
    "tags": [
      "study",
      "habits"
    ]
  },
  {
    "id": "HSK1_005",
    "hsk": 1,
    "chinese": "这个苹果不大，但是很甜，我很喜欢吃。",
    "answer": "Quả táo này không lớn nhưng rất ngọt, tôi rất thích ăn.",
    "keywords": [
      "苹果",
      "甜",
      "喜欢",
      "吃"
    ],
    "difficulty": 2,
    "tags": [
      "food",
      "daily-life"
    ]
  },
  {
    "id": "HSK1_006",
    "hsk": 1,
    "chinese": "爸爸今天不在家，他下午五点才回来。",
    "answer": "Hôm nay bố không ở nhà, đến năm giờ chiều ông ấy mới về.",
    "keywords": [
      "爸爸",
      "下午",
      "回来",
      "家"
    ],
    "difficulty": 2,
    "tags": [
      "family",
      "time"
    ]
  },
  {
    "id": "HSK1_007",
    "hsk": 1,
    "chinese": "我不会写这个汉字，你可以教我吗？",
    "answer": "Tôi không biết viết chữ Hán này, bạn có thể dạy tôi không?",
    "keywords": [
      "写",
      "汉字",
      "可以",
      "教"
    ],
    "difficulty": 2,
    "tags": [
      "study",
      "communication"
    ]
  },
  {
    "id": "HSK1_008",
    "hsk": 1,
    "chinese": "天气冷了，出门的时候别忘了多穿衣服。",
    "answer": "Trời lạnh rồi, khi ra ngoài đừng quên mặc thêm quần áo.",
    "keywords": [
      "天气",
      "冷",
      "出门",
      "衣服"
    ],
    "difficulty": 3,
    "tags": [
      "health",
      "daily-life"
    ]
  },
  {
    "id": "HSK1_009",
    "hsk": 1,
    "chinese": "妹妹正在房间里做作业，请不要说话。",
    "answer": "Em gái đang làm bài tập trong phòng, xin đừng nói chuyện.",
    "keywords": [
      "妹妹",
      "房间",
      "做作业",
      "说话"
    ],
    "difficulty": 2,
    "tags": [
      "family",
      "study"
    ]
  },
  {
    "id": "HSK1_010",
    "hsk": 1,
    "chinese": "我想买一本有意思的书，周末在家看。",
    "answer": "Tôi muốn mua một cuốn sách thú vị để cuối tuần đọc ở nhà.",
    "keywords": [
      "买",
      "书",
      "周末",
      "有意思"
    ],
    "difficulty": 2,
    "tags": [
      "study",
      "shopping"
    ]
  },
  {
    "id": "HSK1_011",
    "hsk": 1,
    "chinese": "老师说，只要每天学习一点儿，就会有进步。",
    "answer": "Thầy giáo nói rằng chỉ cần mỗi ngày học một chút thì sẽ tiến bộ.",
    "keywords": [
      "老师",
      "每天",
      "学习",
      "进步"
    ],
    "difficulty": 3,
    "tags": [
      "study",
      "motivation"
    ]
  },
  {
    "id": "HSK1_012",
    "hsk": 1,
    "chinese": "我们家离学校不远，走路只要十分钟。",
    "answer": "Nhà chúng tôi không xa trường, đi bộ chỉ mất mười phút.",
    "keywords": [
      "离",
      "学校",
      "走路",
      "分钟"
    ],
    "difficulty": 2,
    "tags": [
      "school",
      "daily-life"
    ]
  },
  {
    "id": "HSK1_013",
    "hsk": 1,
    "chinese": "奶奶身体很好，每天都去公园走一走。",
    "answer": "Bà nội rất khỏe, ngày nào cũng đi dạo trong công viên.",
    "keywords": [
      "奶奶",
      "身体",
      "公园",
      "每天"
    ],
    "difficulty": 2,
    "tags": [
      "family",
      "health"
    ]
  },
  {
    "id": "HSK1_014",
    "hsk": 1,
    "chinese": "我没有很多钱，但是我愿意帮助朋友。",
    "answer": "Tôi không có nhiều tiền nhưng tôi sẵn lòng giúp đỡ bạn bè.",
    "keywords": [
      "钱",
      "愿意",
      "帮助",
      "朋友"
    ],
    "difficulty": 3,
    "tags": [
      "friends",
      "values"
    ]
  },
  {
    "id": "HSK1_015",
    "hsk": 1,
    "chinese": "这杯茶有点儿热，你等一会儿再喝吧。",
    "answer": "Cốc trà này hơi nóng, bạn đợi một lát rồi hãy uống.",
    "keywords": [
      "茶",
      "热",
      "等",
      "喝"
    ],
    "difficulty": 2,
    "tags": [
      "food",
      "daily-life"
    ]
  },
  {
    "id": "HSK1_016",
    "hsk": 1,
    "chinese": "他第一次来中国，所以对这里的一切都很好奇。",
    "answer": "Đây là lần đầu anh ấy đến Trung Quốc nên rất tò mò về mọi thứ ở đây.",
    "keywords": [
      "第一次",
      "中国",
      "所以",
      "好奇"
    ],
    "difficulty": 3,
    "tags": [
      "travel",
      "culture"
    ]
  },
  {
    "id": "HSK1_017",
    "hsk": 1,
    "chinese": "妈妈做的饭不但好吃，而且很健康。",
    "answer": "Cơm mẹ nấu không chỉ ngon mà còn rất tốt cho sức khỏe.",
    "keywords": [
      "妈妈",
      "好吃",
      "健康",
      "饭"
    ],
    "difficulty": 3,
    "tags": [
      "family",
      "health"
    ]
  },
  {
    "id": "HSK1_018",
    "hsk": 1,
    "chinese": "我找不到手机了，你看见它了吗？",
    "answer": "Tôi không tìm thấy điện thoại, bạn có nhìn thấy nó không?",
    "keywords": [
      "找不到",
      "手机",
      "看见"
    ],
    "difficulty": 2,
    "tags": [
      "daily-life",
      "communication"
    ]
  },
  {
    "id": "HSK1_019",
    "hsk": 1,
    "chinese": "如果明天天气好，我们就一起去爬山。",
    "answer": "Nếu ngày mai thời tiết đẹp, chúng ta sẽ cùng đi leo núi.",
    "keywords": [
      "明天",
      "天气",
      "一起",
      "爬山"
    ],
    "difficulty": 3,
    "tags": [
      "travel",
      "friends"
    ]
  },
  {
    "id": "HSK1_020",
    "hsk": 1,
    "chinese": "我最喜欢春天，因为花开了，天气也不冷。",
    "answer": "Tôi thích mùa xuân nhất vì hoa nở và thời tiết cũng không lạnh.",
    "keywords": [
      "喜欢",
      "春天",
      "因为",
      "花"
    ],
    "difficulty": 2,
    "tags": [
      "nature",
      "daily-life"
    ]
  },
  {
    "id": "HSK1_021",
    "hsk": 1,
    "chinese": "他每天晚上都复习今天学过的生词。",
    "answer": "Tối nào anh ấy cũng ôn lại những từ mới đã học trong ngày.",
    "keywords": [
      "每天",
      "晚上",
      "复习",
      "生词"
    ],
    "difficulty": 3,
    "tags": [
      "study",
      "habits"
    ]
  },
  {
    "id": "HSK1_022",
    "hsk": 1,
    "chinese": "别担心，慢慢说，我能听懂你的意思。",
    "answer": "Đừng lo, cứ nói chậm thôi, tôi có thể hiểu ý bạn.",
    "keywords": [
      "担心",
      "慢慢",
      "听懂",
      "意思"
    ],
    "difficulty": 3,
    "tags": [
      "communication",
      "encouragement"
    ]
  },
  {
    "id": "HSK1_023",
    "hsk": 1,
    "chinese": "我姐姐喜欢旅游，她去过很多城市。",
    "answer": "Chị gái tôi thích du lịch và đã từng đến nhiều thành phố.",
    "keywords": [
      "姐姐",
      "旅游",
      "去过",
      "城市"
    ],
    "difficulty": 2,
    "tags": [
      "family",
      "travel"
    ]
  },
  {
    "id": "HSK1_024",
    "hsk": 1,
    "chinese": "今天是爷爷的生日，我们给他准备了礼物。",
    "answer": "Hôm nay là sinh nhật ông nội, chúng tôi đã chuẩn bị quà cho ông.",
    "keywords": [
      "爷爷",
      "生日",
      "准备",
      "礼物"
    ],
    "difficulty": 2,
    "tags": [
      "family",
      "celebration"
    ]
  },
  {
    "id": "HSK1_025",
    "hsk": 1,
    "chinese": "这件衣服很好看，可是颜色不太适合我。",
    "answer": "Bộ quần áo này rất đẹp nhưng màu sắc không hợp với tôi lắm.",
    "keywords": [
      "衣服",
      "好看",
      "颜色",
      "适合"
    ],
    "difficulty": 3,
    "tags": [
      "shopping",
      "daily-life"
    ]
  },
  {
    "id": "HSK1_026",
    "hsk": 1,
    "chinese": "学习汉语不容易，但是我每天都很开心。",
    "answer": "Học tiếng Trung không dễ nhưng ngày nào tôi cũng cảm thấy vui.",
    "keywords": [
      "学习",
      "汉语",
      "容易",
      "开心"
    ],
    "difficulty": 2,
    "tags": [
      "study",
      "motivation"
    ]
  },
  {
    "id": "HSK1_027",
    "hsk": 1,
    "chinese": "公共汽车快来了，我们不要再等朋友了。",
    "answer": "Xe buýt sắp đến rồi, chúng ta đừng đợi bạn nữa.",
    "keywords": [
      "公共汽车",
      "快",
      "等",
      "朋友"
    ],
    "difficulty": 3,
    "tags": [
      "travel",
      "time"
    ]
  },
  {
    "id": "HSK1_028",
    "hsk": 1,
    "chinese": "我生病的时候，朋友给我送来了水果。",
    "answer": "Khi tôi bị ốm, bạn đã mang trái cây đến cho tôi.",
    "keywords": [
      "生病",
      "朋友",
      "送",
      "水果"
    ],
    "difficulty": 3,
    "tags": [
      "friends",
      "health"
    ]
  },
  {
    "id": "HSK1_029",
    "hsk": 1,
    "chinese": "房间虽然不大，但是有一张很舒服的床。",
    "answer": "Căn phòng tuy không lớn nhưng có một chiếc giường rất thoải mái.",
    "keywords": [
      "房间",
      "舒服",
      "床"
    ],
    "difficulty": 2,
    "tags": [
      "home",
      "daily-life"
    ]
  },
  {
    "id": "HSK1_030",
    "hsk": 1,
    "chinese": "今天做不完的事情，可以明天继续做。",
    "answer": "Những việc hôm nay chưa làm xong có thể tiếp tục vào ngày mai.",
    "keywords": [
      "今天",
      "事情",
      "明天",
      "继续"
    ],
    "difficulty": 3,
    "tags": [
      "work",
      "motivation"
    ]
  }
]